androidvideo/__init__.py
androidvideo/__main__.py
androidvideo/androidvideo.py
androidvideo-1.0.0.dist-info/DESCRIPTION.rst
androidvideo-1.0.0.dist-info/METADATA
androidvideo-1.0.0.dist-info/RECORD
androidvideo-1.0.0.dist-info/WHEEL
androidvideo-1.0.0.dist-info/entry_points.txt
androidvideo-1.0.0.dist-info/metadata.json
androidvideo-1.0.0.dist-info/top_level.txt
