Metadata-Version: 2.0
Name: androidvideo
Version: 1.0.0
Summary: Create Android compatible videos that play in ANY Android device without third party software.
Home-page: https://github.com/CarloRodriguez/androidvideo
Author: Carlo Eduardo Rodriguez Espino
Author-email: carloeduardorodriguez@gmail.com
License: GPL
Download-URL: https://github.com/CarloRodriguez/androidvideo/archive/master.zip
Keywords: android video videos compatible play
Platform: UNKNOWN
Classifier: Development Status :: 5 - Production/Stable
Classifier: Intended Audience :: Developers
Classifier: Topic :: Utilities
Classifier: Programming Language :: Python :: 2.7
